[
  {
    "word": "natură",
    "definition": "Lumea vie din jurul nostru"
  },
  {
    "word": "universul",
    "definition": "Tot ce există în spațiu"
  },
  {
    "word": "pământul",
    "definition": "Planetă pe care trăim"
  },
  {
    "word": "soarele",
    "definition": "Steaua sistemului solar"
  },
  {
    "word": "lună",
    "definition": "Satelitul natural al Pământului"
  },
  {
    "word": "stele",
    "definition": "Corpuri cerești luminoase"
  },
  {
    "word": "cosmos",
    "definition": "Universul în totalitatea să"
  },
  {
    "word": "galaxia",
    "definition": "Sistem vast de stele"
  },
  {
    "word": "spațiu",
    "definition": "Vastitatea în afara Pământului"
  },
  {
    "word": "gravitație",
    "definition": "Forță care atrage masele"
  },
  {
    "word": "oceane",
    "definition": "Întinderi vaste de apă sărată"
  },
  {
    "word": "munții",
    "definition": "Forme de relief înalte"
  },
  {
    "word": "pădure",
    "definition": "Zonă cu multi copaci deși"
  },
  {
    "word": "deșert",
    "definition": "Zonă aridă cu nisip"
  },
  {
    "word": "râuri",
    "definition": "Cursuri de apă curgătoare"
  },
  {
    "word": "lacuri",
    "definition": "Întinderi de apă inconjurate de uscat"
  },
  {
    "word": "câmpii",
    "definition": "Întinderi de teren plat"
  },
  {
    "word": "insulele",
    "definition": "Bucăți de pământ în apă"
  },
  {
    "word": "vulcanul",
    "definition": "Munte cu activitate magmatică"
  },
  {
    "word": "cutremur",
    "definition": "Mișcare bruscă a scoarței"
  },
  {
    "word": "tsunami",
    "definition": "Val uriaș de apă oceanică"
  },
  {
    "word": "furtună",
    "definition": "Fenomen meteorologic violent"
  },
  {
    "word": "ploaia",
    "definition": "Precipitație din nori"
  },
  {
    "word": "zăpadă",
    "definition": "Precipitație solidă albă"
  },
  {
    "word": "vântul",
    "definition": "Mișcarea maselor de aer"
  },
  {
    "word": "ceață",
    "definition": "Vapori condensati la sol"
  },
  {
    "word": "curcubeu",
    "definition": "Fenomen optic multicolor"
  },
  {
    "word": "tunet",
    "definition": "Zgomot din furtună electrică"
  },
  {
    "word": "fulger",
    "definition": "Descărcare electrică din furtună"
  },
  {
    "word": "anotimpuri",
    "definition": "Cele patru perioade ale anului"
  },
  {
    "word": "varietate",
    "definition": "Mulțimea formelor de viață"
  },
  {
    "word": "ecosistem",
    "definition": "Sistem de viață într-un mediu"
  },
  {
    "word": "evoluția",
    "definition": "Schimbarea speciilor în timp"
  },
  {
    "word": "extincție",
    "definition": "Dispariția unei specii"
  },
  {
    "word": "poluare",
    "definition": "Contaminarea mediului natural"
  },
  {
    "word": "climatul",
    "definition": "Condițiile meteo pe termen lung"
  },
  {
    "word": "încălzire",
    "definition": "Creșterea temperaturii globale"
  },
  {
    "word": "reciclare",
    "definition": "Refolosirea materialelor uzate"
  },
  {
    "word": "energia",
    "definition": "Forță din natură de folosit"
  },
  {
    "word": "oxigenul",
    "definition": "Gazul esențial respirației"
  },
  {
    "word": "apă",
    "definition": "Elementul vital al vieții"
  },
  {
    "word": "focul",
    "definition": "Element de căldură și lumină"
  },
  {
    "word": "solul",
    "definition": "Elementul solid al naturii"
  },
  {
    "word": "aerul",
    "definition": "Elementul gazos al naturii"
  },
  {
    "word": "plantă",
    "definition": "Organism vegetal al naturii"
  },
  {
    "word": "animal",
    "definition": "Organism viu mobil"
  },
  {
    "word": "bacterie",
    "definition": "Organism viu microscopic"
  },
  {
    "word": "virusul",
    "definition": "Entitate infecțioasă microscopică"
  },
  {
    "word": "ciupercă",
    "definition": "Organism fără clorofilă"
  },
  {
    "word": "viață",
    "definition": "Proprietatea de a există și trai"
  }
]